MANIFEST.in
setup.py
sgtnclient/I18N.py
sgtnclient/__init__.py
sgtnclient/sgtn_bykey.py
sgtnclient/sgtn_client.py
sgtnclient/sgtn_locale.py
sgtnclient/sgtn_properties.py
sgtnclient/sgtn_util.py
sgtnclient_test.egg-info/PKG-INFO
sgtnclient_test.egg-info/SOURCES.txt
sgtnclient_test.egg-info/dependency_links.txt
sgtnclient_test.egg-info/requires.txt
sgtnclient_test.egg-info/top_level.txt
test/test_properties_parser.py
test/test_sgtn_bykey.py
test/test_sgtn_client.py
test/test_sgtn_multitask.py
test/test_sgtn_util.py