Metadata-Version: 1.1
Name: sgtnclient-test
Version: 0.6.0.0
Summary: Singleton Client
Home-page: https://github.com/vmware/singleton/tree/g11n-python-client
Author: Jasper Jin
Author-email: jasperj@vmware.com
License: MIT
Platform: UNKNOWN
Classifier: Operating System :: OS Independent
